kete-2.1.5.dist-info/METADATA
kete-2.1.5.dist-info/WHEEL
kete-2.1.5.dist-info/licenses/LICENSE
kete/__init__.py
kete/_core.abi3.so
kete/cache.py
kete/constants.py
kete/conversion.py
kete/covariance.py
kete/deprecation.py
kete/flux.py
kete/fov.py
kete/horizons.py
kete/irsa.py
kete/mpc.py
kete/neos.py
kete/plot.py
kete/population.py
kete/power_law.py
kete/propagation.py
kete/ptf.py
kete/rust/covariance.rs
kete/rust/desigs.rs
kete/rust/elements.rs
kete/rust/fitting.rs
kete/rust/flux/common.rs
kete/rust/flux/mod.rs
kete/rust/flux/models.rs
kete/rust/flux/reflected.rs
kete/rust/fovs/checks.rs
kete/rust/fovs/collection.rs
kete/rust/fovs/definitions.rs
kete/rust/fovs/mod.rs
kete/rust/frame.rs
kete/rust/horizons.rs
kete/rust/kepler.rs
kete/rust/lib.rs
kete/rust/maybe_vec.rs
kete/rust/nongrav.rs
kete/rust/propagation.rs
kete/rust/simult_states.rs
kete/rust/spice/ck.rs
kete/rust/spice/daf.rs
kete/rust/spice/mod.rs
kete/rust/spice/pck.rs
kete/rust/spice/sclk.rs
kete/rust/spice/spk.rs
kete/rust/state.rs
kete/rust/state_transition.rs
kete/rust/time.rs
kete/rust/utils.rs
kete/rust/vector.rs
kete/shape.py
kete/spherex.py
kete/spice.py
kete/state_transition.py
kete/tap.py
kete/time.py
kete/vector.py
kete/wise.py
kete/ztf.py
kete-2.1.5.dist-info/RECORD
