Metadata-Version: 2.4
Name: kete
Version: 2.1.5
Classifier: Programming Language :: Python :: 3
Classifier: Intended Audience :: Education
Classifier: Intended Audience :: Science/Research
Classifier: Topic :: Scientific/Engineering :: Mathematics
Classifier: Topic :: Scientific/Engineering :: Physics
Requires-Dist: astropy>=5.3.4
Requires-Dist: matplotlib
Requires-Dist: matplotlib-label-lines<=0.8.0
Requires-Dist: numpy>=1.24
Requires-Dist: pandas
Requires-Dist: requests
Requires-Dist: scipy
Requires-Dist: ruff ; extra == 'dev'
Requires-Dist: pytest ; extra == 'dev'
Requires-Dist: pytest-cov ; extra == 'dev'
Requires-Dist: sphinx ; extra == 'dev'
Requires-Dist: autodoc ; extra == 'dev'
Requires-Dist: sphinx-gallery ; extra == 'dev'
Requires-Dist: mypy ; extra == 'dev'
Requires-Dist: types-requests ; extra == 'dev'
Requires-Dist: sphinx-rtd-theme ; extra == 'dev'
Requires-Dist: click ; extra == 'dev'
Requires-Dist: sphinx ; extra == 'docs'
Requires-Dist: autodoc ; extra == 'docs'
Requires-Dist: sphinx-gallery ; extra == 'docs'
Requires-Dist: sphinx-rtd-theme ; extra == 'docs'
Requires-Dist: click ; extra == 'docs'
Requires-Dist: pytz ; extra == 'docs'
Provides-Extra: dev
Provides-Extra: docs
License-File: LICENSE
Summary: Kete Asteroid Survey Tools
Author-email: Dar Dahlen <dardahlen@gmail.com>
License-Expression: BSD-3-Clause
Requires-Python: >=3.9
Project-URL: homepage, https://github.com/dahlend/kete
